AWKDE/AWKDE.py
AWKDE/__init__.py
AWKDE-0.1.2.dist-info/METADATA
AWKDE-0.1.2.dist-info/WHEEL
AWKDE-0.1.2.dist-info/top_level.txt
AWKDE-0.1.2.dist-info/RECORD
